tensorflowcv/__init__.py
tensorflowcv/model_provider.py
tensorflowcv/models/__init__.py
tensorflowcv/models/alexnet.py
tensorflowcv/models/channelnet.py
tensorflowcv/models/common.py
tensorflowcv/models/darknet.py
tensorflowcv/models/darknet53.py
tensorflowcv/models/densenet.py
tensorflowcv/models/igcv3.py
tensorflowcv/models/menet.py
tensorflowcv/models/mnasnet.py
tensorflowcv/models/mnasnet_old.py
tensorflowcv/models/mobilenet.py
tensorflowcv/models/mobilenetv2.py
tensorflowcv/models/mobilenetv3.py
tensorflowcv/models/model_store.py
tensorflowcv/models/preresnet.py
tensorflowcv/models/resnet.py
tensorflowcv/models/resnext.py
tensorflowcv/models/senet.py
tensorflowcv/models/sepreresnet.py
tensorflowcv/models/seresnet.py
tensorflowcv/models/seresnext.py
tensorflowcv/models/shufflenet.py
tensorflowcv/models/shufflenetv2.py
tensorflowcv/models/shufflenetv2b.py
tensorflowcv/models/squeezenet.py
tensorflowcv/models/squeezenext.py
tensorflowcv/models/vgg.py
tensorflowcv/models/zfnet.py
tensorflowcv-0.0.38.dist-info/LICENSE.txt
tensorflowcv-0.0.38.dist-info/METADATA
tensorflowcv-0.0.38.dist-info/WHEEL
tensorflowcv-0.0.38.dist-info/top_level.txt
tensorflowcv-0.0.38.dist-info/RECORD
